Metadata-Version: 1.0
Name: General-Gaussian-Binomial-Distributions
Version: 0.1
Summary: General, Gaussian, Binomial and Distributions
Home-page: UNKNOWN
Author: Maria Milman and Udacity
Author-email: UNKNOWN
License: UNKNOWN
Platform: UNKNOWN
